{
    "components": [
        {
            "type": "life",
            "current": 200,
            "max": 200
        },
        {
            "type": "mana",
            "current": 50,
            "max": 50
        },
        {
            "type": "tag",
            "to": "ENEMY"
        },
        {
            "type": "collision",
            "box": {
                "width": 10.0,
                "height": 10.0
            }
        },
        {
            "type": "spellbook",
            "spells": [
                "spells/ice_lance.json"
            ]
        },
        {
            "type": "velocity",
            "speed": 1.5
        },
        {
            "type": "texture",
            "file_path": "characters/monsters/wolf/textures/wolf_c.png"
        }
    ]
}